{
  "updated_at": "2026-06-26 17:41 KST",
  "coverage": {
    "items": 4296,
    "oldest": "2025-06-27",
    "newest": "2026-06-26",
    "days_covered": 365,
    "complete": true
  },
  "weekly": [
    {
      "topic": "재건축·재개발·정비사업",
      "count": 153,
      "trend_label": "직전 동일기간보다 72건 증가",
      "examples": [
        "[서울 구청장별 정비사업 전략은] 최우선 공약은 재건축·재개발… 전담팀 가동 등 총력 - 한국주택경제신문",
        "【인사이트 서평】정비사업의 현재와 미래를 읽다 - 『2026 재개발·재건축 트렌드』 - 고령자주택신문",
        "고양시, 일산신도시 재건축 용적률 350% 검토…1기 신도시 정비사업 탄력 - 건설이코노미뉴스"
      ]
    },
    {
      "topic": "주택공급·공공주택",
      "count": 23,
      "trend_label": "직전 동일기간보다 12건 증가",
      "examples": [
        "■공공주택 특별법 시행규칙 [별표 5의2] 통합공공임대주택의 입주자 자격( - 국가법령정보센터",
        "■공공주택 특별법 시행규칙 [별표 6의4] 공공임대주택의 입주자 선정 특례 - 국가법령정보센터",
        "■ 공공주택 특별법 시행규칙 [별표 6의5] 지분적립형 분양주택의 입주자 선 - 국가법령정보센터"
      ]
    },
    {
      "topic": "철도·광역교통·역세권",
      "count": 12,
      "trend_label": "직전 동일기간보다 4건 증가",
      "examples": [
        "수색역 역세권, '어르신 안심주택' 696세대 공급 본격화…맞춤형 돌봄시설 완비",
        "서울역세권(청파동1가 46번지 일대) 도시정비형 재개발사업 추진위원회 정비사업전문관리업자 선정 입찰공고 - 한국주택경제신문",
        "서울역세권(청파동)도시정비형 재개발사업 추진위 정비사업전문관리업자·설계자 선정 - 하우징헤럴드"
      ]
    },
    {
      "topic": "토지·부동산시장",
      "count": 12,
      "trend_label": "직전 동일기간보다 3건 증가",
      "examples": [
        "부동산원, 재개발·재건축 조합 운영 컨설팅…7월 전국 시행 - 연합뉴스",
        "부동산원, 초기 재건축·재개발 조합 맞춤형 컨설팅 나선다 - 더팩트",
        "[부동산 돋보기] 딜레마 빠진 재개발·재건축 - v.daum.net"
      ]
    },
    {
      "topic": "국토계획·용도지역·규제",
      "count": 9,
      "trend_label": "직전 동일기간보다 1건 감소",
      "examples": [
        "민경선 고양시장 당선인 \"일산신도시 재건축 용적률 350% 검토\" - 연합뉴스",
        "\"일산 재건축 용적률 350%로 뚫린다\"…민경선 호, 파격 상향 검토 - 아시아경제",
        "고양시, 일산신도시 재건축 용적률 350% 검토…1기 신도시 정비사업 탄력 - 건설이코노미뉴스"
      ]
    },
    {
      "topic": "지역소멸·균형발전",
      "count": 7,
      "trend_label": "직전 동일기간보다 1건 증가",
      "examples": [
        "[단독] 균형발전 살리고 ‘수도권 배제’는 푼다 - 인천일보",
        "“영동권 잉여전력, AI 산업 성장동력으로”…국가균형발전 모델 제시 - v.daum.net",
        "“영동권 잉여전력, AI 산업 성장동력으로”…국가균형발전 모델 제안 - v.daum.net"
      ]
    },
    {
      "topic": "기후위기·탄소중립·녹색건축",
      "count": 7,
      "trend_label": "직전 동일기간보다 3건 감소",
      "examples": [
        "기후위기·AI 시대 아리수는 어떻게 대응할까…서울시 「서울워터 2025」 발간",
        "도시하천유역 침수피해방지대책법 시행령 - 국민참여입법센터",
        "기후위기, AI에서 해법 찾는다…6월 25~26일 서울 기후테크 컨퍼런스 개최"
      ]
    },
    {
      "topic": "도시안전·재난 대응",
      "count": 6,
      "trend_label": "직전 동일기간보다 2건 증가",
      "examples": [
        "도시하천유역 침수피해방지대책법 시행령 - 국민참여입법센터",
        "(자료제공) ''빈틈없이 살핀다''… 오세훈 시장, 관악구 침수취약지역 점검",
        "전용호 경기도 북부소방재난본부장 전담 직무대리 취임 - 경기도뉴스포털"
      ]
    },
    {
      "topic": "건축정책·공공건축",
      "count": 4,
      "trend_label": "직전 동일기간보다 4건 증가",
      "examples": [
        "2026 공공기관 관계자 대상 공공건축 기초교육 안내 | 공지사항 | auri 소식 | 소식 - 건축공간연구원",
        "서울시, ‘건축안전세미나’개최…민간공사장 안전관리 강화",
        "(석간) 서울시, 공공건축 설계공모 백서「모두의 아이디어2」 출간…30개 공모·152개 작품 한눈에 - seoul.go.kr"
      ]
    },
    {
      "topic": "도시재생·빈집·원도심",
      "count": 3,
      "trend_label": "직전 동일기간보다 5건 감소",
      "examples": [
        "고흥의 밤, 수제맥주와 야시장이 빛난다…도시재생 '브루어리' 경제활력 엔진 가동 - 연합뉴스",
        "전북 도시재생 관계자들, 충주서 지속가능성 해법 찾다 - 전라매일",
        "부여 향교 '도시재생사업'이라는데…8년째 공사 중인 이유는 - v.daum.net"
      ]
    }
  ],
  "monthly": [
    {
      "topic": "재건축·재개발·정비사업",
      "count": 246,
      "trend_label": "직전 동일기간보다 144건 증가",
      "examples": [
        "[서울 구청장별 정비사업 전략은] 최우선 공약은 재건축·재개발… 전담팀 가동 등 총력 - 한국주택경제신문",
        "【인사이트 서평】정비사업의 현재와 미래를 읽다 - 『2026 재개발·재건축 트렌드』 - 고령자주택신문",
        "고양시, 일산신도시 재건축 용적률 350% 검토…1기 신도시 정비사업 탄력 - 건설이코노미뉴스"
      ]
    },
    {
      "topic": "주택공급·공공주택",
      "count": 49,
      "trend_label": "직전 동일기간보다 38건 증가",
      "examples": [
        "■공공주택 특별법 시행규칙 [별표 5의2] 통합공공임대주택의 입주자 자격( - 국가법령정보센터",
        "■공공주택 특별법 시행규칙 [별표 6의4] 공공임대주택의 입주자 선정 특례 - 국가법령정보센터",
        "■ 공공주택 특별법 시행규칙 [별표 6의5] 지분적립형 분양주택의 입주자 선 - 국가법령정보센터"
      ]
    },
    {
      "topic": "철도·광역교통·역세권",
      "count": 26,
      "trend_label": "직전 동일기간보다 18건 증가",
      "examples": [
        "현행 자치법규 > 법규명 > 서울특별시 도시철도건설기준에 관한 규칙 - 국가법령정보센터",
        "자치법규 > 서울특별시 도시철도건설기준에 관한 규칙 - 국가법령정보센터",
        "29일 ‘부산진역~부산역 철도지하화통합개발사업 현장’ 찾아 추진현황 점검, 성공적인 사업 추진을 위해 유관기관 간 긴밀한 협력 당부 - 국토교통부"
      ]
    },
    {
      "topic": "국토계획·용도지역·규제",
      "count": 24,
      "trend_label": "직전 동일기간보다 2건 증가",
      "examples": [
        "민경선 고양시장 당선인 \"일산신도시 재건축 용적률 350% 검토\" - 연합뉴스",
        "\"일산 재건축 용적률 350%로 뚫린다\"…민경선 호, 파격 상향 검토 - 아시아경제",
        "고양시, 일산신도시 재건축 용적률 350% 검토…1기 신도시 정비사업 탄력 - 건설이코노미뉴스"
      ]
    },
    {
      "topic": "토지·부동산시장",
      "count": 24,
      "trend_label": "직전 동일기간보다 8건 증가",
      "examples": [
        "집값 어느새 45억 ‘쑥’...잠실주공5단지 재건축 속도 [김경민의 부동산NOW] - 매일경제",
        "부동산원, 재개발·재건축 조합 운영 컨설팅…7월 전국 시행 - 연합뉴스",
        "부동산원, 초기 재건축·재개발 조합 맞춤형 컨설팅 나선다 - 더팩트"
      ]
    },
    {
      "topic": "기후위기·탄소중립·녹색건축",
      "count": 19,
      "trend_label": "직전 동일기간보다 16건 증가",
      "examples": [
        "기후위기·AI 시대 아리수는 어떻게 대응할까…서울시 「서울워터 2025」 발간",
        "도시하천유역 침수피해방지대책법 시행령 - 국민참여입법센터",
        "기후위기, AI에서 해법 찾는다…6월 25~26일 서울 기후테크 컨퍼런스 개최"
      ]
    },
    {
      "topic": "도시안전·재난 대응",
      "count": 14,
      "trend_label": "직전 동일기간보다 10건 증가",
      "examples": [
        "도시하천유역 침수피해방지대책법 시행령 - 국민참여입법센터",
        "(자료제공) ''빈틈없이 살핀다''… 오세훈 시장, 관악구 침수취약지역 점검",
        "전용호 경기도 북부소방재난본부장 전담 직무대리 취임 - 경기도뉴스포털"
      ]
    },
    {
      "topic": "지역소멸·균형발전",
      "count": 13,
      "trend_label": "직전 동일기간보다 13건 증가",
      "examples": [
        "[단독] 균형발전 살리고 ‘수도권 배제’는 푼다 - 인천일보",
        "“영동권 잉여전력, AI 산업 성장동력으로”…국가균형발전 모델 제시 - v.daum.net",
        "“영동권 잉여전력, AI 산업 성장동력으로”…국가균형발전 모델 제안 - v.daum.net"
      ]
    },
    {
      "topic": "스마트시티·AI·디지털전환",
      "count": 13,
      "trend_label": "직전 동일기간보다 10건 증가",
      "examples": [
        "자율주행·UAM·인공지능(AI)시티 기술 전시, 역대 최대 규모(81개 기관, 409개 부스), 현대차·KAI 등 참여 확대, 국민 체험형 전시와 전문가 특강·투자상담회 등 풍성 - 국토교통부",
        "롯데, 베트남 '에코 스마트시티' 재개 공식화…현지기업과 파트너십 - 인사이드비나",
        "행복청, 행복도시 스마트시티 고도화 방안 모색 - 뉴데일리 충청세종"
      ]
    },
    {
      "topic": "도시재생·빈집·원도심",
      "count": 12,
      "trend_label": "직전 동일기간보다 7건 증가",
      "examples": [
        "고흥의 밤, 수제맥주와 야시장이 빛난다…도시재생 '브루어리' 경제활력 엔진 가동 - 연합뉴스",
        "전북 도시재생 관계자들, 충주서 지속가능성 해법 찾다 - 전라매일",
        "부여 향교 '도시재생사업'이라는데…8년째 공사 중인 이유는 - v.daum.net"
      ]
    }
  ],
  "yearly": [
    {
      "topic": "재건축·재개발·정비사업",
      "count": 1261,
      "trend_label": "최근 1년 누적",
      "examples": [
        "[서울 구청장별 정비사업 전략은] 최우선 공약은 재건축·재개발… 전담팀 가동 등 총력 - 한국주택경제신문",
        "【인사이트 서평】정비사업의 현재와 미래를 읽다 - 『2026 재개발·재건축 트렌드』 - 고령자주택신문",
        "고양시, 일산신도시 재건축 용적률 350% 검토…1기 신도시 정비사업 탄력 - 건설이코노미뉴스"
      ]
    },
    {
      "topic": "주택공급·공공주택",
      "count": 164,
      "trend_label": "최근 1년 누적",
      "examples": [
        "(서리풀) 서울 서리풀1 공공주택지구 지정 고시… ’29년 첫 분양 목표, (남현) 지구계획 승인으로 서울 내 832호 공급계획 본격화 - 국토교통부",
        "■공공주택 특별법 시행규칙 [별표 5의2] 통합공공임대주택의 입주자 자격( - 국가법령정보센터",
        "■공공주택 특별법 시행규칙 [별표 6의4] 공공임대주택의 입주자 선정 특례 - 국가법령정보센터"
      ]
    },
    {
      "topic": "국토계획·용도지역·규제",
      "count": 145,
      "trend_label": "최근 1년 누적",
      "examples": [
        "민경선 고양시장 당선인 \"일산신도시 재건축 용적률 350% 검토\" - 연합뉴스",
        "\"일산 재건축 용적률 350%로 뚫린다\"…민경선 호, 파격 상향 검토 - 아시아경제",
        "고양시, 일산신도시 재건축 용적률 350% 검토…1기 신도시 정비사업 탄력 - 건설이코노미뉴스"
      ]
    },
    {
      "topic": "토지·부동산시장",
      "count": 122,
      "trend_label": "최근 1년 누적",
      "examples": [
        "집값 어느새 45억 ‘쑥’...잠실주공5단지 재건축 속도 [김경민의 부동산NOW] - 매일경제",
        "\"아버지가 물려준 집인데\"…송파 재건축 아파트 입주권 운명 갈렸다 [조선규의 부동산 산책] - 한국경제",
        "현실화율은 전년과 동일한 69% 적용 : 부동산 시세 변동만 공시가격에 반영, 전년 대비 전국 평균 9.16% 상승, 평균 상승률 대비 높게 상승한 지역은 서울이 유일, 서울 지역별 상승률 : 강남3구 24.7%, 한강 인접 자치구 23.13%, 그 외 자치구 6.93% - 국토교통부"
      ]
    },
    {
      "topic": "철도·광역교통·역세권",
      "count": 93,
      "trend_label": "최근 1년 누적",
      "examples": [
        "현행 자치법규 > 법규명 > 서울특별시 도시철도건설기준에 관한 규칙 - 국가법령정보센터",
        "자치법규 > 서울특별시 도시철도건설기준에 관한 규칙 - 국가법령정보센터",
        "29일 ‘부산진역~부산역 철도지하화통합개발사업 현장’ 찾아 추진현황 점검, 성공적인 사업 추진을 위해 유관기관 간 긴밀한 협력 당부 - 국토교통부"
      ]
    },
    {
      "topic": "도시재생·빈집·원도심",
      "count": 75,
      "trend_label": "최근 1년 누적",
      "examples": [
        "성남 구도심 변신 예고 | 성남 원도심 정비에 날개… ‘생활권 재개발’ 가속도 페달 - 한국주택경제신문",
        "김포시, 원도심 재개발·도시재생 본격화 가시적 성과 - 전국매일신문",
        "[FOCUS 경기] 광주시 도시재생, 새롭게 태어난 원도심 - 경인일보"
      ]
    },
    {
      "topic": "스마트시티·AI·디지털전환",
      "count": 54,
      "trend_label": "최근 1년 누적",
      "examples": [
        "자율주행·UAM·인공지능(AI)시티 기술 전시, 역대 최대 규모(81개 기관, 409개 부스), 현대차·KAI 등 참여 확대, 국민 체험형 전시와 전문가 특강·투자상담회 등 풍성 - 국토교통부",
        "롯데, 베트남 '에코 스마트시티' 재개 공식화…현지기업과 파트너십 - 인사이드비나",
        "행복청, 행복도시 스마트시티 고도화 방안 모색 - 뉴데일리 충청세종"
      ]
    },
    {
      "topic": "도시안전·재난 대응",
      "count": 47,
      "trend_label": "최근 1년 누적",
      "examples": [
        "도시하천유역 침수피해방지대책법 시행령 - 국민참여입법센터",
        "(자료제공) ''빈틈없이 살핀다''… 오세훈 시장, 관악구 침수취약지역 점검",
        "전용호 경기도 북부소방재난본부장 전담 직무대리 취임 - 경기도뉴스포털"
      ]
    },
    {
      "topic": "지역소멸·균형발전",
      "count": 34,
      "trend_label": "최근 1년 누적",
      "examples": [
        "인구감소지역에 더 높은 세제 감면율 적용…\"지역 균형발전 촉진\" - 대한민국 정책브리핑",
        "[단독] 균형발전 살리고 ‘수도권 배제’는 푼다 - 인천일보",
        "“영동권 잉여전력, AI 산업 성장동력으로”…국가균형발전 모델 제시 - v.daum.net"
      ]
    },
    {
      "topic": "기후위기·탄소중립·녹색건축",
      "count": 31,
      "trend_label": "최근 1년 누적",
      "examples": [
        "폭염 취약계층 지원, AI 침수예측… 서울시, 10월까지 '여름철 종합대책' 가동 - seoul.go.kr",
        "기후위기·AI 시대 아리수는 어떻게 대응할까…서울시 「서울워터 2025」 발간",
        "도시하천유역 침수피해방지대책법 시행령 - 국민참여입법센터"
      ]
    }
  ]
}